torchadf/__init__.py
torchadf/nn/__init__.py
torchadf/nn/functional.py
torchadf/nn/modules/__init__.py
torchadf/nn/modules/activation.py
torchadf/nn/modules/container.py
torchadf/nn/modules/conv.py
torchadf/nn/modules/flatten.py
torchadf/nn/modules/linear.py
torchadf/nn/modules/pooling.py
torch_adf-22.1.0.dist-info/LICENSE
torch_adf-22.1.0.dist-info/METADATA
torch_adf-22.1.0.dist-info/WHEEL
torch_adf-22.1.0.dist-info/top_level.txt
torch_adf-22.1.0.dist-info/RECORD
