Metadata-Version: 2.1
Name: torch-adf
Version: 22.1.0
Summary: Assumed Density Filtering (ADF) Probabilistic Networks
Home-page: https://github.com/jmaces/torch-adf
Author: Jan Maces
Author-email: janmaces@gmail.com
Maintainer: Jan Maces
Maintainer-email: janmaces@gmail.com
License: MIT
Keywords: pytorch,torch,probabilistic-models,deep-learning,deep-neural-networks,machine-learning
Classifier: Development Status :: 3 - Alpha
Classifier: Intended Audience :: Developers
Classifier: Intended Audience :: Science/Research
Classifier: Natural Language :: English
Classifier: License :: OSI Approved :: MIT License
Classifier: Operating System :: OS Independent
Classifier: Programming Language :: Python
Classifier: Programming Language :: Python :: 3
Classifier: Programming Language :: Python :: 3.6
Classifier: Programming Language :: Python :: 3.7
Classifier: Programming Language :: Python :: 3.8
Classifier: Topic :: Scientific/Engineering :: Information Analysis
Classifier: Topic :: Scientific/Engineering :: Artificial Intelligence
Classifier: Topic :: Scientific/Engineering :: Mathematics
Requires-Python: >=3.6
License-File: LICENSE
Requires-Dist: torch
Requires-Dist: numpy
Provides-Extra: dev
Requires-Dist: coverage ; extra == 'dev'
Requires-Dist: hypothesis[numpy] ; extra == 'dev'
Requires-Dist: scipy ; extra == 'dev'
Requires-Dist: pytest (>=4.3.0) ; extra == 'dev'
Requires-Dist: sphinx (>=1.6.5) ; extra == 'dev'
Requires-Dist: numpydoc ; extra == 'dev'
Requires-Dist: pre-commit ; extra == 'dev'
Provides-Extra: docs
Requires-Dist: sphinx (>=1.6.5) ; extra == 'docs'
Requires-Dist: numpydoc ; extra == 'docs'
Provides-Extra: tests
Requires-Dist: coverage ; extra == 'tests'
Requires-Dist: hypothesis[numpy] ; extra == 'tests'
Requires-Dist: scipy ; extra == 'tests'
Requires-Dist: pytest (>=4.3.0) ; extra == 'tests'
